{"creepers": 2, "scatters": 2, "petaled": 2, "windless": 2, "mooing": 2, "furue": 2, "cumulus": 3, "dusky": 2, "carven": 2, "beholders": 3, "watersplash": 3, "evenfall": 2, "bathwater": 3, "whippoorwill": 3, "priestling": 2, "tendrils": 2, "archways": 2, "froglings": 2, "camellia": 3, "lichened": 2, "moonrise": 2, "windblown": 2, "pattering": 3, "nightingales": 3, "hibiscus": 3, "dewdrop": 2, "cloudbanks": 2, "spiritless": 3, "atsuta": 3, "storks": 1, "inuyasha": 4, "battlers": 3, "fie": 1, "persimmons": 3, "ridgelines": 2, "woodcutter": 3, "swordhand": 2, "cloudbank": 2, "asakura": 4, "nursemaid": 3, "paperweights": 3, "tendrilled": 2, "deepener": 3, "morningglory": 4, "dragonfly": 3, "oranged": 2, "wintery": 2, "wisteria": 3, "skims": 1, "foregather": 3, "samisen": 3, "treeline": 2, "shadeless": 2, "samuri": 2, "treehouse": 2, "colour": 2, "yowl": 1, "stretchings": 2}